__init__.py
zoslogs/__init__.py
zoslogs/utils.py
zoslogs/zoslogs.py
zoslogs/zosmessage.py
zoslogs-0.3.0.dist-info/licenses/LICENSE
zoslogs-0.3.0.dist-info/METADATA
zoslogs-0.3.0.dist-info/WHEEL
zoslogs-0.3.0.dist-info/entry_points.txt
zoslogs-0.3.0.dist-info/top_level.txt
zoslogs-0.3.0.dist-info/RECORD
