Metadata-Version: 2.4
Name: zoslogs
Version: 0.3.0
Summary: Library for breaking z/OS log files up into individual messages
Author-email: Kevin McKenzie <kmckenzi@us.ibm.com>
License-Expression: Apache-2.0
Project-URL: Homepage, https://github.com/Tam-Lin/zoslogs
Project-URL: Repository, https://github.com/Tam-Lin/zoslogs.git
Project-URL: Changelog, https://github.com/Tam-Lin/zoslogs/blob/master/HISTORY.rst
Keywords: zoslogs,z/OS,mainframe
Classifier: Development Status :: 4 - Beta
Classifier: Intended Audience :: Developers
Classifier: Natural Language :: English
Classifier: Programming Language :: Python :: 3
Classifier: Programming Language :: Python :: 3.9
Classifier: Programming Language :: Python :: 3.10
Classifier: Programming Language :: Python :: 3.11
Classifier: Programming Language :: Python :: 3.12
Classifier: Programming Language :: Python :: 3.13
Requires-Python: >=3.6
License-File: LICENSE
Requires-Dist: tqdm
Dynamic: license-file
